flow360/__init__.py
flow360/accounts_utils.py
flow360/cli/__init__.py
flow360/cli/api_set_func.py
flow360/cli/app.py
flow360/cli/dict_utils.py
flow360/cloud/__init__.py
flow360/cloud/compress_upload.py
flow360/cloud/flow360_requests.py
flow360/cloud/heartbeat.py
flow360/cloud/http_util.py
flow360/cloud/rest_api.py
flow360/cloud/s3_utils.py
flow360/cloud/security.py
flow360/cloud/utils.py
flow360/cloud/webbrowser.py
flow360/component/__init__.py
flow360/component/case.py
flow360/component/constants.py
flow360/component/folder.py
flow360/component/geometry.py
flow360/component/interfaces.py
flow360/component/project.py
flow360/component/project_utils.py
flow360/component/resource_base.py
flow360/component/results/base_results.py
flow360/component/results/case_results.py
flow360/component/results/results_utils.py
flow360/component/simulation/__init__.py
flow360/component/simulation/blueprint/__init__.py
flow360/component/simulation/blueprint/core/__init__.py
flow360/component/simulation/blueprint/core/context.py
flow360/component/simulation/blueprint/core/dependency_graph.py
flow360/component/simulation/blueprint/core/expressions.py
flow360/component/simulation/blueprint/core/function.py
flow360/component/simulation/blueprint/core/generator.py
flow360/component/simulation/blueprint/core/parser.py
flow360/component/simulation/blueprint/core/resolver.py
flow360/component/simulation/blueprint/core/statements.py
flow360/component/simulation/blueprint/core/types.py
flow360/component/simulation/blueprint/utils/__init__.py
flow360/component/simulation/blueprint/utils/operators.py
flow360/component/simulation/conversion.py
flow360/component/simulation/entity_info.py
flow360/component/simulation/entity_operation.py
flow360/component/simulation/exposed_units.py
flow360/component/simulation/folder.py
flow360/component/simulation/framework/__init__.py
flow360/component/simulation/framework/base_model.py
flow360/component/simulation/framework/entity_base.py
flow360-25.7.7.dist-info/METADATA
flow360-25.7.7.dist-info/WHEEL
flow360-25.7.7.dist-info/entry_points.txt
flow360-25.7.7.dist-info/licenses/LICENSE
flow360-25.7.7.dist-info/RECORD
