Metadata-Version: 2.4
Name: flow360
Version: 25.7.7
Summary: Flow360 Python Client
License-File: LICENSE
Author: Flexcompute
Author-email: support@flexcompute.com
Requires-Python: >=3.9,<3.13
Classifier: Programming Language :: Python :: 3
Classifier: Programming Language :: Python :: 3.9
Classifier: Programming Language :: Python :: 3.10
Classifier: Programming Language :: Python :: 3.11
Classifier: Programming Language :: Python :: 3.12
Provides-Extra: docs
Requires-Dist: autodoc_pydantic ; extra == "docs"
Requires-Dist: black[jupyter] (>=24.10.0,<25.0.0)
Requires-Dist: boto3 (>=1.24.63,<2.0.0)
Requires-Dist: cairosvg ; extra == "docs"
Requires-Dist: click (>=8.1.3,<9.0.0)
Requires-Dist: h5py (>=3.10.0,<4.0.0)
Requires-Dist: ipython ; extra == "docs"
Requires-Dist: jinja2 (>=3.1.2) ; extra == "docs"
Requires-Dist: jupyter ; extra == "docs"
Requires-Dist: matplotlib (>=3.6.2,<4.0.0) ; python_version >= "3.10" and python_version < "4.0"
Requires-Dist: matplotlib (>=3.6.2,<4.0.0) ; python_version >= "3.9" and python_version < "4.0"
Requires-Dist: myst-parser ; extra == "docs"
Requires-Dist: nbconvert (>=7.11.0) ; extra == "docs"
Requires-Dist: nbdime ; extra == "docs"
Requires-Dist: nbsphinx (>=0.8.7) ; extra == "docs"
Requires-Dist: numexpr (>=2.10.1,<3.0.0)
Requires-Dist: numpy (>=2.0,<3.0.0) ; python_version >= "3.10" and python_version < "4.0"
Requires-Dist: numpy (>=2.0,<3.0.0) ; python_version >= "3.11" and python_version < "4.0"
Requires-Dist: numpy (>=2.0,<3.0.0) ; python_version >= "3.12" and python_version < "4.0"
Requires-Dist: numpy (>=2.0,<3.0.0) ; python_version >= "3.9" and python_version < "4.0"
Requires-Dist: numpydoc (>=1.8.0,<2.0.0) ; extra == "docs"
Requires-Dist: pandas (>=2.2.1,<3.0.0)
Requires-Dist: prettyprinttree (>=2.0.1,<3.0.0)
Requires-Dist: pydantic (>=2.8,<2.12)
Requires-Dist: pydata-sphinx-theme (>=0.13.3) ; extra == "docs"
Requires-Dist: pylatex (>=1.4.2,<2.0.0)
Requires-Dist: pylint (>=3.1.0,<4.0.0)
Requires-Dist: pytest (>=7.1.2,<8.0.0)
Requires-Dist: pyyaml (>=6.0.1,<7.0.0)
Requires-Dist: readthedocs-sphinx-search ; extra == "docs"
Requires-Dist: requests (>=2.32.4,<3.0.0)
Requires-Dist: rich (>=13.3.4,<14.0.0)
Requires-Dist: scipy (>=1.13.0,<2.0.0) ; python_version >= "3.9" and python_version < "4.0"
Requires-Dist: scipy (>=1.14.0,<2.0.0) ; python_version >= "3.10" and python_version < "4.0"
Requires-Dist: sphinx (>=7) ; extra == "docs"
Requires-Dist: sphinx-book-theme (>=1.0.1) ; extra == "docs"
Requires-Dist: sphinx-copybutton (>=0.5.2) ; extra == "docs"
Requires-Dist: sphinx-favicon ; extra == "docs"
Requires-Dist: sphinx-notfound-page ; extra == "docs"
Requires-Dist: sphinx-prompt ; extra == "docs"
Requires-Dist: sphinx-sitemap (>=2.5.1) ; extra == "docs"
Requires-Dist: sphinx-tabs ; extra == "docs"
Requires-Dist: sphinx_design ; extra == "docs"
Requires-Dist: sphinx_paramlinks ; extra == "docs"
Requires-Dist: sphinx_toolbox ; extra == "docs"
Requires-Dist: sphinxcontrib-mermaid ; extra == "docs"
Requires-Dist: sphinxcontrib-svg2pdfconverter ; extra == "docs"
Requires-Dist: sphinxemoji ; extra == "docs"
Requires-Dist: toml (>=0.10.2,<0.11.0)
Requires-Dist: unyt (>=3.0.0,<4.0.0)
Requires-Dist: zstandard (>=0.21.0,<0.22.0)
